mylib/__init__.py
mylib/funct.py
mylibKG7456/__init__.py
mylibKG7456/funct.py
mylibKG7456-0.0.1.dist-info/METADATA
mylibKG7456-0.0.1.dist-info/WHEEL
mylibKG7456-0.0.1.dist-info/top_level.txt
mylibKG7456-0.0.1.dist-info/RECORD
